{
  "id": "1baf560e-a162-4322-b206-70c3b69cf34f",
  "prevId": "00000000-0000-0000-0000-000000000000",
  "version": "7",
  "dialect": "postgresql",
  "tables": {
    "public.BookCons": {
      "name": "BookCons",
      "schema": "",
      "columns": {
        "id": {
          "name": "id",
          "type": "varchar(36)",
          "primaryKey": true,
          "notNull": true
        },
        "otpCode": {
          "name": "otpCode",
          "type": "text",
          "primaryKey": false,
          "notNull": true
        },
        "otpCodeCreatedAt": {
          "name": "otpCodeCreatedAt",
          "type": "timestamp with time zone",
          "primaryKey": false,
          "notNull": true,
          "default": "now()"
        },
        "photo": {
          "name": "photo",
          "type": "text",
          "primaryKey": false,
          "notNull": true
        },
        "name": {
          "name": "name",
          "type": "varchar(64)",
          "primaryKey": false,
          "notNull": true
        },
        "fatherName": {
          "name": "fatherName",
          "type": "varchar(64)",
          "primaryKey": false,
          "notNull": true
        },
        "grandFatherName": {
          "name": "grandFatherName",
          "type": "varchar(64)",
          "primaryKey": false,
          "notNull": true
        },
        "gender": {
          "name": "gender",
          "type": "Gender",
          "typeSchema": "public",
          "primaryKey": false,
          "notNull": true
        },
        "dateOfBirth": {
          "name": "dateOfBirth",
          "type": "timestamp with time zone",
          "primaryKey": false,
          "notNull": true
        },
        "placeOfBirth": {
          "name": "placeOfBirth",
          "type": "text",
          "primaryKey": false,
          "notNull": true
        },
        "height": {
          "name": "height",
          "type": "real",
          "primaryKey": false,
          "notNull": true
        },
        "eyeColor": {
          "name": "eyeColor",
          "type": "text",
          "primaryKey": false,
          "notNull": true
        },
        "hairColor": {
          "name": "hairColor",
          "type": "text",
          "primaryKey": false,
          "notNull": true
        },
        "occupation": {
          "name": "occupation",
          "type": "text",
          "primaryKey": false,
          "notNull": true
        },
        "region": {
          "name": "region",
          "type": "text",
          "primaryKey": false,
          "notNull": true
        },
        "country": {
          "name": "country",
          "type": "text",
          "primaryKey": false,
          "notNull": true
        },
        "zone": {
          "name": "zone",
          "type": "text",
          "primaryKey": false,
          "notNull": true
        },
        "city": {
          "name": "city",
          "type": "text",
          "primaryKey": false,
          "notNull": true
        },
        "woreda": {
          "name": "woreda",
          "type": "text",
          "primaryKey": false,
          "notNull": true
        },
        "streetName": {
          "name": "streetName",
          "type": "text",
          "primaryKey": false,
          "notNull": true
        },
        "kebele": {
          "name": "kebele",
          "type": "text",
          "primaryKey": false,
          "notNull": true
        },
        "phoneNumber": {
          "name": "phoneNumber",
          "type": "text",
          "primaryKey": false,
          "notNull": true
        },
        "houseNo": {
          "name": "houseNo",
          "type": "text",
          "primaryKey": false,
          "notNull": true
        },
        "poBox": {
          "name": "poBox",
          "type": "text",
          "primaryKey": false,
          "notNull": false
        },
        "email": {
          "name": "email",
          "type": "text",
          "primaryKey": false,
          "notNull": true
        },
        "createdAt": {
          "name": "createdAt",
          "type": "timestamp with time zone",
          "primaryKey": false,
          "notNull": true,
          "default": "now()"
        },
        "updatedAt": {
          "name": "updatedAt",
          "type": "timestamp with time zone",
          "primaryKey": false,
          "notNull": true,
          "default": "CURRENT_TIMESTAMP"
        }
      },
      "indexes": {},
      "foreignKeys": {},
      "compositePrimaryKeys": {},
      "uniqueConstraints": {
        "BookCons_otpCode_unique": {
          "name": "BookCons_otpCode_unique",
          "nullsNotDistinct": false,
          "columns": [
            "otpCode"
          ]
        },
        "BookCons_email_unique": {
          "name": "BookCons_email_unique",
          "nullsNotDistinct": false,
          "columns": [
            "email"
          ]
        }
      },
      "policies": {},
      "checkConstraints": {},
      "isRLSEnabled": false
    }
  },
  "enums": {
    "public.Gender": {
      "name": "Gender",
      "schema": "public",
      "values": [
        "Male",
        "Female",
        "Other"
      ]
    }
  },
  "schemas": {},
  "sequences": {},
  "roles": {},
  "policies": {},
  "views": {},
  "_meta": {
    "columns": {},
    "schemas": {},
    "tables": {}
  }
}